ppgen/__init__.py
ppgen/chinese_words.txt
ppgen/cli.py
ppgen/core.py
ppgen/evaluator.py
ppgen-0.1.0.dist-info/METADATA
ppgen-0.1.0.dist-info/WHEEL
ppgen-0.1.0.dist-info/entry_points.txt
ppgen-0.1.0.dist-info/top_level.txt
ppgen-0.1.0.dist-info/RECORD
