Metadata-Version: 2.2
Name: ppgen
Version: 0.1.0
Summary: A password/passphrase generator that uses Chinese pinyin
Author-email: Keli Hu <dev@keli.hu>
License: MIT
Classifier: Development Status :: 3 - Alpha
Classifier: Environment :: Console
Classifier: Intended Audience :: End Users/Desktop
Classifier: License :: OSI Approved :: MIT License
Classifier: Programming Language :: Python :: 3
Classifier: Topic :: Security
Classifier: Topic :: Utilities
Requires-Dist: click
